README.rst
setup.py
ocspd/__init__.py
ocspd/__main__.py
ocspd.egg-info/PKG-INFO
ocspd.egg-info/SOURCES.txt
ocspd.egg-info/dependency_links.txt
ocspd.egg-info/entry_points.txt
ocspd.egg-info/requires.txt
ocspd.egg-info/top_level.txt
ocspd/colourlog/__init__.py
ocspd/colourlog/__main__.py
ocspd/core/__init__.py
ocspd/core/certfinder.py
ocspd/core/certmodel.py
ocspd/core/certparser.py
ocspd/core/daemon.py
ocspd/core/excepthandler.py
ocspd/core/exceptions.py
ocspd/core/ocspadder.py
ocspd/core/ocsprenewer.py
ocspd/core/taskcontext.py
ocspd/scheduling/__init__.py
ocspd/util/__init__.py
ocspd/util/cache.py
ocspd/util/functions.py
ocspd/util/ocsp.py
scripts/ocspd.service